{
  "allFiles": [
    {
      "file": "/storage/emulated/0/AndroidIDEProjects/DIMUSICPLAY/gradle.properties",
      "selection": {
        "end": {
          "column": 0,
          "index": 0,
          "line": 0
        },
        "start": {
          "column": 0,
          "index": 0,
          "line": 0
        }
      }
    },
    {
      "file": "/storage/emulated/0/AndroidIDEProjects/DIMUSICPLAY/gradle/wrapper/gradle-wrapper.properties",
      "selection": {
        "end": {
          "column": 77,
          "index": 142,
          "line": 2
        },
        "start": {
          "column": 77,
          "index": 142,
          "line": 2
        }
      }
    }
  ],
  "selectedFile": "/storage/emulated/0/AndroidIDEProjects/DIMUSICPLAY/gradle/wrapper/gradle-wrapper.properties"
}